market_analytics/__init__.py
market_analytics/company.py
market_analytics/dashboard.py
market_analytics/market.py
market_analytics/secret.py
market_analytics/security.py
market_analytics/twitter.py
market_analytics/update.py
market_analytics/visualize.py
market_analytics/wiki.py
market_analytics/data/stock_symbols.csv
Market_Analytics-0.0.12.dist-info/LICENSE.txt
Market_Analytics-0.0.12.dist-info/METADATA
Market_Analytics-0.0.12.dist-info/WHEEL
Market_Analytics-0.0.12.dist-info/top_level.txt
Market_Analytics-0.0.12.dist-info/RECORD
