Metadata-Version: 2.1
Name: Market-Analytics
Version: 0.0.12
Summary: Toolkit for Stock Market analysis and visualization
Home-page: https://github.com/wesleyLaurence/Stock-Market-Analytics
Author: Wesley Laurence
Author-email: wesleylaurencetech@gmail.com
License: UNKNOWN
Platform: UNKNOWN
Classifier: Programming Language :: Python :: 3
Classifier: License :: OSI Approved :: MIT License
Classifier: Operating System :: OS Independent
Requires-Python: >=3.6
Requires-Dist: numpy
Requires-Dist: pandas
Requires-Dist: matplotlib
Requires-Dist: seaborn
Requires-Dist: pymongo
Requires-Dist: yahoo-fin
Requires-Dist: flask
Requires-Dist: werkzeug
Requires-Dist: cryptography
Requires-Dist: tweepy
Requires-Dist: wikipedia
Requires-Dist: dnspython
Requires-Dist: requests-html
